gpt_tools/__init__.py
gpt_tools/chat.py
gpt_tools/git.py
kaar_gpt_tools-0.2.0.dist-info/METADATA
kaar_gpt_tools-0.2.0.dist-info/WHEEL
kaar_gpt_tools-0.2.0.dist-info/entry_points.txt
kaar_gpt_tools-0.2.0.dist-info/RECORD
