Metadata-Version: 2.1
Name: kaar-gpt-tools
Version: 0.2.0
Summary: GPT Tools
Project-URL: Documentation, https://github.com/kaar/gpt-tools#readme
Project-URL: Issues, https://github.com/kaar/gpt-tools/issues
Project-URL: Source, https://github.com/kaar/gpt-tools
Author-email: Caspar Nettelbladt <caspar.n@gmail.com>
License-Expression: MIT
Classifier: License :: OSI Approved :: MIT License
Classifier: Operating System :: OS Independent
Classifier: Programming Language :: Python :: 3
Classifier: Topic :: Software Development :: Libraries :: Python Modules
Requires-Python: >=3.7
Requires-Dist: kaar-gpt
